{"cameraMode":{"drawMode":0,"name":"Shaded","section":"Shading Mode"},"sceneLighting":true,"audioPlay":false,"sceneViewState":{"showFog":true,"showMaterialUpdate":false,"showSkybox":true,"showFlares":true,"showImageEffects":true,"showParticleSystems":true,"showVisualEffectGraphs":true,"m_FxEnabled":true},"in2DMode":false,"pivot":{"x":11.24201774597168,"y":-0.719994068145752,"z":-7.222963809967041},"rotation":{"x":-0.14773106575012208,"y":0.6361594200134277,"z":-0.12585239112377168,"w":-0.7467519044876099},"size":10.6812744140625,"orthographic":false}